dataclass_argparse/__init__.py
dataclass_argparse/dataclass_argparse.py
dataclass_argparse/example_joined_args.py
dataclass_argparse/example_separate_args.py
dataclass_argparse-0.1.2.dist-info/LICENSE
dataclass_argparse-0.1.2.dist-info/METADATA
dataclass_argparse-0.1.2.dist-info/WHEEL
dataclass_argparse-0.1.2.dist-info/top_level.txt
dataclass_argparse-0.1.2.dist-info/RECORD
