Metadata-Version: 2.1
Name: dataclass-argparse
Version: 0.1.2
Summary: argparse with a type annotated namespace dataclass
Home-page: https://github.com/fynnbe/dataclass-argparse
Author: Fynn Beuttenmüller
License: UNKNOWN
Project-URL: Bug Reports, https://github.com/fynnbe/dataclass-argparse/issues
Project-URL: Source, https://github.com/fynnbe/dataclass-argparse
Platform: UNKNOWN
Classifier: Development Status :: 3 - Alpha
Classifier: Intended Audience :: Developers
Classifier: Programming Language :: Python :: 3.8
Classifier: Programming Language :: Python :: 3.9
Provides-Extra: dev
Requires-Dist: pre-commit ; extra == 'dev'
Provides-Extra: test
Requires-Dist: mypy ; extra == 'test'
